Mappyfile08ZhongwenWendang/README.md
Mappyfile08ZhongwenWendang/__init__.py
Mappyfile08ZhongwenWendang/__main__.py
Mappyfile08ZhongwenWendang/file.epub
Mappyfile08ZhongwenWendang/index.html
Mappyfile08ZhongwenWendang/css/__init__.py
Mappyfile08ZhongwenWendang/css/annotations.css
Mappyfile08ZhongwenWendang/css/main.css
Mappyfile08ZhongwenWendang/css/normalize.css
Mappyfile08ZhongwenWendang/css/popup.css
Mappyfile08ZhongwenWendang/font/__init__.py
Mappyfile08ZhongwenWendang/font/fontello.eot
Mappyfile08ZhongwenWendang/font/fontello.svg
Mappyfile08ZhongwenWendang/font/fontello.ttf
Mappyfile08ZhongwenWendang/font/fontello.woff
Mappyfile08ZhongwenWendang/img/__init__.py
Mappyfile08ZhongwenWendang/img/annotator-glyph-sprite.png
Mappyfile08ZhongwenWendang/img/annotator-icon-sprite.png
Mappyfile08ZhongwenWendang/img/apple-touch-icon.png
Mappyfile08ZhongwenWendang/img/cancelfullscreen.png
Mappyfile08ZhongwenWendang/img/close.png
Mappyfile08ZhongwenWendang/img/fullscreen.png
Mappyfile08ZhongwenWendang/img/loader.gif
Mappyfile08ZhongwenWendang/img/menu-icon.png
Mappyfile08ZhongwenWendang/img/save.png
Mappyfile08ZhongwenWendang/img/saved.png
Mappyfile08ZhongwenWendang/img/settings-s.png
Mappyfile08ZhongwenWendang/img/settings.png
Mappyfile08ZhongwenWendang/img/star.png
Mappyfile08ZhongwenWendang/js/__init__.py
Mappyfile08ZhongwenWendang/js/epub.js
Mappyfile08ZhongwenWendang/js/epub.min.js
Mappyfile08ZhongwenWendang/js/epub.min.map
Mappyfile08ZhongwenWendang/js/hooks.min.js
Mappyfile08ZhongwenWendang/js/hooks.min.map
Mappyfile08ZhongwenWendang/js/reader.js
Mappyfile08ZhongwenWendang/js/reader.js.map
Mappyfile08ZhongwenWendang/js/reader.min.js
Mappyfile08ZhongwenWendang/js/reader.min.map
Mappyfile08ZhongwenWendang/js/hooks/__init__.py
Mappyfile08ZhongwenWendang/js/hooks/extensions/__init__.py
Mappyfile08ZhongwenWendang/js/hooks/extensions/highlight.js
Mappyfile08ZhongwenWendang/js/libs/__init__.py
Mappyfile08ZhongwenWendang/js/libs/jquery.min.js
mappyfile_0_8_zhongwen_wendang-2024.3.5.0.dist-info/METADATA
mappyfile_0_8_zhongwen_wendang-2024.3.5.0.dist-info/WHEEL
mappyfile_0_8_zhongwen_wendang-2024.3.5.0.dist-info/entry_points.txt
mappyfile_0_8_zhongwen_wendang-2024.3.5.0.dist-info/top_level.txt
mappyfile_0_8_zhongwen_wendang-2024.3.5.0.dist-info/RECORD
